{
  "packConfigId": "knowledge-answering:basic-demo",
  "packConfigVersion": "0.1.0",
  "archetypeId": "knowledge-answering",
  "archetypeVersion": "0.1.0",
  "variantId": "basic-demo",
  "variantVersion": "0.1.0",
  "locale": "en",
  "capabilities": {
    "questionIntake": { "value": true, "source": "confirmedByUser", "required": true },
    "knowledgeRetrieval": { "value": true, "source": "confirmedByUser", "required": true },
    "confidenceEvaluation": { "value": true, "source": "confirmedByUser", "required": true },
    "sourceCitation": { "value": true, "source": "confirmedByUser" },
    "answerGeneration": { "value": true, "source": "confirmedByUser", "required": true },
    "clarification": { "value": true, "source": "confirmedByUser" },
    "handoff": { "value": true, "source": "confirmedByUser", "required": true }
  },
  "businessObjects": [
    {
      "objectId": "question",
      "label": { "en": "Question", "zhCN": "问题" },
      "fields": ["question_id", "question_text", "topic"]
    },
    {
      "objectId": "demo_knowledge_snippet",
      "label": { "en": "Demo knowledge snippet", "zhCN": "演示知识片段" },
      "fields": ["demo_snippet_id", "demo_title", "freshness_label"]
    }
  ],
  "rules": {
    "knowledgePolicy.minConfidence": {
      "value": 0.72,
      "source": "defaultFromPack",
      "required": true,
      "label": { "en": "Demo minimum confidence", "zhCN": "演示最低置信度" }
    },
    "knowledgePolicy.lowConfidenceStrategy": {
      "value": "ask_clarification",
      "source": "confirmedByUser",
      "required": true
    },
    "knowledgePolicy.noAnswerStrategy": {
      "value": "no_answer_with_reason",
      "source": "confirmedByUser",
      "required": true
    },
    "knowledgePolicy.staleKnowledgeStrategy": {
      "value": "warn_user",
      "source": "confirmedByUser",
      "required": true
    },
    "knowledgePolicy.sensitiveQuestionStrategy": {
      "value": "handoff",
      "source": "confirmedByUser",
      "required": true
    },
    "sourcePolicy.requireSourceCitation": {
      "value": true,
      "source": "confirmedByUser",
      "required": true
    },
    "sourcePolicy.minSourceCount": {
      "value": 1,
      "source": "defaultFromPack",
      "required": true
    },
    "sourcePolicy.allowUnverifiedAnswer": {
      "value": false,
      "source": "confirmedByUser",
      "required": true
    },
    "sourcePolicy.showSourceSummary": {
      "value": true,
      "source": "confirmedByUser"
    },
    "responseStyle.tone": {
      "value": "neutral",
      "source": "confirmedByUser",
      "required": true
    },
    "responseStyle.includeSources": {
      "value": true,
      "source": "confirmedByUser"
    },
    "responseStyle.includeUncertainty": {
      "value": true,
      "source": "confirmedByUser"
    },
    "responseStyle.includeNextSteps": {
      "value": true,
      "source": "confirmedByUser"
    }
  },
  "policies": {
    "knowledgeAnswering.failClosed": {
      "value": true,
      "source": "defaultFromPack",
      "label": { "en": "Knowledge-answering fail-closed", "zhCN": "知识回答 fail-closed" }
    },
    "sourceCitation.required": {
      "value": true,
      "source": "defaultFromPack",
      "label": { "en": "Source citation required", "zhCN": "要求来源引用" }
    }
  },
  "adapters": [
    {
      "adapterId": "demo-knowledge-provider",
      "mode": "mock",
      "contractRef": "contracts/demo-knowledge-provider-contract.md",
      "fieldMappings": {
        "questionText": "question_text",
        "demoSnippetId": "demo_snippet_id",
        "demoTitle": "demo_title"
      },
      "containsRealEndpoint": false,
      "containsSecret": false
    },
    {
      "adapterId": "demo-citation-store",
      "mode": "mock",
      "contractRef": "contracts/demo-citation-store-contract.md",
      "fieldMappings": {
        "requiredSourceCount": "min_source_count",
        "sourceSummary": "demo_source_summary"
      },
      "containsRealEndpoint": false,
      "containsSecret": false
    }
  ],
  "templates": [
    {
      "templateId": "answer_with_sources",
      "purpose": "Render a generic demo answer with source placeholders.",
      "text": {
        "value": "Demo answer template with source placeholders.",
        "source": "defaultFromPack"
      }
    },
    {
      "templateId": "low_confidence_clarification",
      "purpose": "Ask a generic clarification when answer confidence is too low.",
      "text": {
        "value": "Demo clarification template for low confidence.",
        "source": "defaultFromPack"
      }
    },
    {
      "templateId": "no_answer_with_reason",
      "purpose": "Explain that the demo flow cannot answer safely.",
      "text": {
        "value": "Demo no-answer template for governed fallback.",
        "source": "defaultFromPack"
      }
    }
  ],
  "tests": [
    {
      "testCaseId": "known_question_answer_with_sources",
      "title": "Known question answer with sources",
      "input": {
        "question_id": "DEMO-Q-KNOWN",
        "question_text": "demo governed answer question",
        "confidence_score": 0.86,
        "demo_source_count": 1
      },
      "expectedOutcome": "answer_with_sources"
    },
    {
      "testCaseId": "low_confidence_asks_clarification",
      "title": "Low confidence asks clarification",
      "input": {
        "question_id": "DEMO-Q-LOW",
        "question_text": "demo ambiguous question",
        "confidence_score": 0.41,
        "demo_source_count": 1
      },
      "expectedOutcome": "ask_clarification"
    }
  ],
  "governance": {
    "environment": "demo",
    "publishable": false,
    "requiresHumanReview": true,
    "unconfirmedFieldPolicy": "block_publish",
    "missingFieldPolicy": "block_compile",
    "sideEffectPolicy": {
      "maxAutoSideEffect": "read",
      "requiresPolicyGuardFrom": "write"
    }
  },
  "metadata": {
    "publicDemo": true,
    "containsCustomerData": false,
    "containsRealKnowledgeAssets": false,
    "containsRealProviderConfig": false
  }
}
